<?xml version="1.0" ?>
<PropertySetDef xmlns:xsi="http://www.w3.org/2001/XMLSchema-instance" xmlns:xsd="http://www.w3.org/2001/XMLSchema" templatetype="PSET_TYPEDRIVENOVERRIDE" xsi:noNamespaceSchemaLocation="http://buildingSMART-tech.org/xml/psd/PSD_IFC4.xsd">
  <IfcVersion version="IFC4X3_DEV_f77d288"/>
  <Name>Pset_BalanceWeightTensionerDesignCriteria</Name>
  <Definition/>
  <Applicability/>
  <ApplicableClasses>
    <ClassName>IfcDiscreteAccessory/TENSIONINGEQUIPMENT</ClassName>
  </ApplicableClasses>
  <ApplicableTypeValue>IfcDiscreteAccessory/TENSIONINGEQUIPMENT</ApplicableTypeValue>
  <PropertyDefs>
    <PropertyDef>
      <Name>ReferenceDistanceRopeToPulley</Name>
      <Definition/>
      <PropertyType>
        <TypePropertyTableValue>
          <Expression/>
          <DefiningValue>
            <DataType type="IfcThermodynamicTemperatureMeasure"/>
          </DefiningValue>
          <DefinedValue>
            <DataType type="IfcPositiveLengthMeasure"/>
          </DefinedValue>
        </TypePropertyTableValue>
      </PropertyType>
    </PropertyDef>
    <PropertyDef>
      <Name>ReferenceDistanceTensionerToGround</Name>
      <Definition/>
      <PropertyType>
        <TypePropertyTableValue>
          <Expression/>
          <DefiningValue>
            <DataType type="IfcThermodynamicTemperatureMeasure"/>
          </DefiningValue>
          <DefinedValue>
            <DataType type="IfcPositiveLengthMeasure"/>
          </DefinedValue>
        </TypePropertyTableValue>
      </PropertyType>
    </PropertyDef>
  </PropertyDefs>
</PropertySetDef>
