<?xml version="1.0" ?>
<PropertySetDef xmlns:xsi="http://www.w3.org/2001/XMLSchema-instance" xmlns:xsd="http://www.w3.org/2001/XMLSchema" templatetype="PSET_TYPEDRIVENOVERRIDE" xsi:noNamespaceSchemaLocation="http://buildingSMART-tech.org/xml/psd/PSD_IFC4.xsd">
  <IfcVersion version="IFC4X3_DEV_5b2157d"/>
  <Name>Pset_ValveTypeCommon</Name>
  <Definition/>
  <Applicability/>
  <ApplicableClasses>
    <ClassName>IfcValve</ClassName>
  </ApplicableClasses>
  <ApplicableTypeValue>IfcValve</ApplicableTypeValue>
  <PropertyDefs>
    <PropertyDef>
      <Name>Reference</Name>
      <Definition/>
      <PropertyType>
        <TypePropertySingleValue>
          <DataType type="IfcIdentifier"/>
        </TypePropertySingleValue>
      </PropertyType>
    </PropertyDef>
    <PropertyDef>
      <Name>Status</Name>
      <Definition/>
      <PropertyType>
        <TypePropertyEnumeratedValue>
          <EnumList name="PEnum_ElementStatus">
            <EnumItem>DEMOLISH</EnumItem>
            <EnumItem>EXISTING</EnumItem>
            <EnumItem>NEW</EnumItem>
            <EnumItem>NOTKNOWN</EnumItem>
            <EnumItem>OTHER</EnumItem>
            <EnumItem>TEMPORARY</EnumItem>
            <EnumItem>UNSET</EnumItem>
          </EnumList>
        </TypePropertyEnumeratedValue>
      </PropertyType>
    </PropertyDef>
    <PropertyDef>
      <Name>ValvePattern</Name>
      <Definition/>
      <PropertyType>
        <TypePropertyEnumeratedValue>
          <EnumList name="PEnum_ValvePattern">
            <EnumItem>ANGLED_2_PORT</EnumItem>
            <EnumItem>CROSSOVER_4_PORT</EnumItem>
            <EnumItem>NOTKNOWN</EnumItem>
            <EnumItem>OTHER</EnumItem>
            <EnumItem>SINGLEPORT</EnumItem>
            <EnumItem>STRAIGHT_2_PORT</EnumItem>
            <EnumItem>STRAIGHT_3_PORT</EnumItem>
            <EnumItem>UNSET</EnumItem>
          </EnumList>
        </TypePropertyEnumeratedValue>
      </PropertyType>
    </PropertyDef>
    <PropertyDef>
      <Name>ValveOperation</Name>
      <Definition/>
      <PropertyType>
        <TypePropertyEnumeratedValue>
          <EnumList name="PEnum_ValveOperation">
            <EnumItem>DROPWEIGHT</EnumItem>
            <EnumItem>FLOAT</EnumItem>
            <EnumItem>HYDRAULIC</EnumItem>
            <EnumItem>LEVER</EnumItem>
            <EnumItem>LOCKSHIELD</EnumItem>
            <EnumItem>MOTORIZED</EnumItem>
            <EnumItem>NOTKNOWN</EnumItem>
            <EnumItem>OTHER</EnumItem>
            <EnumItem>PNEUMATIC</EnumItem>
            <EnumItem>SOLENOID</EnumItem>
            <EnumItem>SPRING</EnumItem>
            <EnumItem>THERMOSTATIC</EnumItem>
            <EnumItem>UNSET</EnumItem>
            <EnumItem>WHEEL</EnumItem>
          </EnumList>
        </TypePropertyEnumeratedValue>
      </PropertyType>
    </PropertyDef>
    <PropertyDef>
      <Name>ValveMechanism</Name>
      <Definition/>
      <PropertyType>
        <TypePropertyEnumeratedValue>
          <EnumList name="PEnum_ValveMechanism">
            <EnumItem>BALL</EnumItem>
            <EnumItem>BUTTERFLY</EnumItem>
            <EnumItem>CONFIGUREDGATE</EnumItem>
            <EnumItem>GLAND</EnumItem>
            <EnumItem>GLOBE</EnumItem>
            <EnumItem>LUBRICATEDPLUG</EnumItem>
            <EnumItem>NEEDLE</EnumItem>
            <EnumItem>NOTKNOWN</EnumItem>
            <EnumItem>OTHER</EnumItem>
            <EnumItem>PARALLELSLIDE</EnumItem>
            <EnumItem>PLUG</EnumItem>
            <EnumItem>UNSET</EnumItem>
            <EnumItem>WEDGEGATE</EnumItem>
          </EnumList>
        </TypePropertyEnumeratedValue>
      </PropertyType>
    </PropertyDef>
    <PropertyDef>
      <Name>Size</Name>
      <Definition/>
      <PropertyType>
        <TypePropertySingleValue>
          <DataType type="IfcPositiveLengthMeasure"/>
        </TypePropertySingleValue>
      </PropertyType>
    </PropertyDef>
    <PropertyDef>
      <Name>TestPressure</Name>
      <Definition/>
      <PropertyType>
        <TypePropertySingleValue>
          <DataType type="IfcPressureMeasure"/>
        </TypePropertySingleValue>
      </PropertyType>
    </PropertyDef>
    <PropertyDef>
      <Name>WorkingPressure</Name>
      <Definition/>
      <PropertyType>
        <TypePropertySingleValue>
          <DataType type="IfcPressureMeasure"/>
        </TypePropertySingleValue>
      </PropertyType>
    </PropertyDef>
    <PropertyDef>
      <Name>FlowCoefficient</Name>
      <Definition/>
      <PropertyType>
        <TypePropertySingleValue>
          <DataType type="IfcReal"/>
        </TypePropertySingleValue>
      </PropertyType>
    </PropertyDef>
    <PropertyDef>
      <Name>CloseOffRating</Name>
      <Definition/>
      <PropertyType>
        <TypePropertySingleValue>
          <DataType type="IfcPressureMeasure"/>
        </TypePropertySingleValue>
      </PropertyType>
    </PropertyDef>
  </PropertyDefs>
</PropertySetDef>
